[
  {
    "name": "The Final Battle",
    "artist": "Tsukasa Saitoh",
    "id": "1nspl7hBhdl6W6GQzbn3V1",
    "added_at": "2023-04-06T12:24:18Z",
    "added_by": "dangreensmith",
    "length_seconds": 298
  },
  {
    "name": "Ornstein & Smough",
    "artist": "Motoi Sakuraba",
    "id": "0UZ8dfdjMEl20o9fArUr5t",
    "added_at": "2023-04-13T01:56:45Z",
    "added_by": "dangreensmith",
    "length_seconds": 170
  },
  {
    "name": "Silver For Monsters...",
    "artist": "Percival Schuttenbach, Marcin Przyby\u0142owicz",
    "id": "1e6i6WC1SW5w6e5u5izQ19",
    "added_at": "2023-04-13T01:50:58Z",
    "added_by": "dangreensmith",
    "length_seconds": 139
  },
  {
    "name": "...Steel For Humans",
    "artist": "Percival Schuttenbach, Marcin Przyby\u0142owicz",
    "id": "1asBfrlvpH0Brn6xcD7yms",
    "added_at": "2023-04-06T12:29:22Z",
    "added_by": "dangreensmith",
    "length_seconds": 87
  },
  {
    "name": "The Trail",
    "artist": "Marcin Przyby\u0142owicz",
    "id": "4diKCx2EUg4CGvDTyCan5H",
    "added_at": "2023-04-13T02:56:47Z",
    "added_by": "dangreensmith",
    "length_seconds": 169
  },
  {
    "name": "The Song Of The Sword-Dancer",
    "artist": "Percival Schuttenbach, Marcin Przyby\u0142owicz",
    "id": "2k6KTdwvApSUnN0maOmIFb",
    "added_at": "2023-04-13T02:57:09Z",
    "added_by": "dangreensmith",
    "length_seconds": 132
  },
  {
    "name": "Birth of a Wish",
    "artist": "\u5ca1\u90e8\u5553\u4e00",
    "id": "1vLOdL2b4k7cwUyJTmr8gS",
    "added_at": "2023-04-13T02:03:26Z",
    "added_by": "dangreensmith",
    "length_seconds": 280
  },
  {
    "name": "God of War",
    "artist": "Bear McCreary",
    "id": "6ZMwwuUOx8kefl32gWOjtY",
    "added_at": "2023-04-13T01:52:07Z",
    "added_by": "dangreensmith",
    "length_seconds": 246
  },
  {
    "name": "Deliverance",
    "artist": "Bear McCreary",
    "id": "5Cg2LlfEdszEW8pH1Pcos1",
    "added_at": "2023-04-13T01:56:52Z",
    "added_by": "dangreensmith",
    "length_seconds": 378
  },
  {
    "name": "The Dragon",
    "artist": "Bear McCreary",
    "id": "3y6ok4gZSvQkDLlu89CwlO",
    "added_at": "2023-04-13T01:59:10Z",
    "added_by": "dangreensmith",
    "length_seconds": 223
  },
  {
    "name": "Soul of Cinder",
    "artist": "Yuka Kitamura",
    "id": "2AmzsY9FSPAnRFuSZkiLXm",
    "added_at": "2023-04-13T01:51:27Z",
    "added_by": "dangreensmith",
    "length_seconds": 351
  },
  {
    "name": "One\u200b-\u200bWinged Angel (Final Fantasy VII)",
    "artist": "Nobuo Uematsu",
    "id": "7GBP9vqKB9o9wcQrkblICD",
    "added_at": "2023-04-13T02:00:13Z",
    "added_by": "dangreensmith",
    "length_seconds": 265
  },
  {
    "name": "Weight of the World - Prelude Version",
    "artist": "\u7956\u5805 \u6b63\u6176",
    "id": "5a5ej2F1HtCb3BX2xrz98A",
    "added_at": "2023-04-13T01:52:51Z",
    "added_by": "dangreensmith",
    "length_seconds": 158
  },
  {
    "name": "Torn from the Heavens/The Dark Colossus Destroys All - Medley Version",
    "artist": "\u7956\u5805 \u6b63\u6176",
    "id": "53z6vNCChujE8UaM231Xhg",
    "added_at": "2023-04-13T01:53:12Z",
    "added_by": "dangreensmith",
    "length_seconds": 398
  },
  {
    "name": "The Worm's Tail",
    "artist": "\u7956\u5805 \u6b63\u6176",
    "id": "0gpp8dE6vnlLszg4uh207H",
    "added_at": "2023-04-13T02:57:37Z",
    "added_by": "dangreensmith",
    "length_seconds": 298
  },
  {
    "name": "Stand Your Ground",
    "artist": "Yoko Shimomura",
    "id": "238Owc9WvZ4HsUD57bcq8o",
    "added_at": "2023-04-13T01:54:27Z",
    "added_by": "dangreensmith",
    "length_seconds": 209
  },
  {
    "name": "Hunt or Be Hunted",
    "artist": "Yoko Shimomura",
    "id": "4mEz48ER9qCPog5uOxP6vL",
    "added_at": "2023-04-13T02:25:48Z",
    "added_by": "dangreensmith",
    "length_seconds": 308
  },
  {
    "name": "Veiled in Black",
    "artist": "Yoko Shimomura",
    "id": "0m04YC2z66cggr4VvZBUMS",
    "added_at": "2023-04-13T02:52:38Z",
    "added_by": "dangreensmith",
    "length_seconds": 201
  },
  {
    "name": "OMNIS LACRIMA",
    "artist": "Yoko Shimomura",
    "id": "4Vy8J8AAM5vzhCQnsxIqjg",
    "added_at": "2023-04-13T01:57:12Z",
    "added_by": "dangreensmith",
    "length_seconds": 271
  },
  {
    "name": "APOCALYPSIS NOCTIS",
    "artist": "Yoko Shimomura",
    "id": "21Bvy2KqGLO0f3QVgvruru",
    "added_at": "2023-04-13T02:32:58Z",
    "added_by": "dangreensmith",
    "length_seconds": 254
  },
  {
    "name": "APOCALYPSIS AQUARIUS",
    "artist": "Yoko Shimomura",
    "id": "4aPltIjGkJx26Y9cBHu14U",
    "added_at": "2023-04-13T02:02:50Z",
    "added_by": "dangreensmith",
    "length_seconds": 252
  },
  {
    "name": "Cleric Beast",
    "artist": "SIE Sound Team",
    "id": "65CefKbmaG0ZkumWSFKbxC",
    "added_at": "2023-04-13T01:56:21Z",
    "added_by": "dangreensmith",
    "length_seconds": 184
  },
  {
    "name": "Reign of the Septims",
    "artist": "Jeremy Soule",
    "id": "4QX9ua1QVyhfAWy73TtrlH",
    "added_at": "2023-04-13T01:58:17Z",
    "added_by": "dangreensmith",
    "length_seconds": 110
  },
  {
    "name": "One They Fear",
    "artist": "Jeremy Soule",
    "id": "1czhAnpBVEcFN9DTLAsfAQ",
    "added_at": "2023-04-13T01:59:36Z",
    "added_by": "dangreensmith",
    "length_seconds": 194
  },
  {
    "name": "Vampire Killer",
    "artist": "Castlevania Sound Team",
    "id": "4HXzm6IXEvVbfzEADMAVng",
    "added_at": "2023-04-13T02:02:24Z",
    "added_by": "dangreensmith",
    "length_seconds": 190
  },
  {
    "name": "Bloody Tears (From \"Castlevania\")",
    "artist": "Anjer",
    "id": "57qXU0ZSCaRPuJwIcolFdn",
    "added_at": "2023-04-13T02:16:47Z",
    "added_by": "dangreensmith",
    "length_seconds": 146
  },
  {
    "name": "Monster Hunter",
    "artist": "Capcom Sound Team",
    "id": "1qteA4p8vKkpMkIKBmMvrl",
    "added_at": "2023-04-13T02:54:48Z",
    "added_by": "dangreensmith",
    "length_seconds": 184
  },
  {
    "name": "Scourge of the Furies",
    "artist": "Darren Korb",
    "id": "2OCOsaORs3HhmybcodGSUH",
    "added_at": "2023-04-13T02:40:34Z",
    "added_by": "dangreensmith",
    "length_seconds": 506
  },
  {
    "name": "God of the Dead",
    "artist": "Darren Korb",
    "id": "65pRSbXmrkdE1HzzIkeLPH",
    "added_at": "2023-04-06T12:27:47Z",
    "added_by": "dangreensmith",
    "length_seconds": 541
  },
  {
    "name": "The Unseen Ones",
    "artist": "Darren Korb, Masahiro Aoki, daisuke kurosawa",
    "id": "5lfoxLv56xGnP8CDLfhA7r",
    "added_at": "2023-04-13T02:04:02Z",
    "added_by": "dangreensmith",
    "length_seconds": 258
  },
  {
    "name": "Fallen Angel",
    "artist": "\u7956\u5805 \u6b63\u6176",
    "id": "5CS69gZzcV9yRwSt44mcFT",
    "added_at": "2023-04-13T02:14:21Z",
    "added_by": "dangreensmith",
    "length_seconds": 270
  },
  {
    "name": "Torn from the Heavens",
    "artist": "\u7956\u5805 \u6b63\u6176, FILM SCORE",
    "id": "2Hf5MJo5GjGwUIySaUxiLJ",
    "added_at": "2023-04-13T02:16:16Z",
    "added_by": "dangreensmith",
    "length_seconds": 311
  },
  {
    "name": "Ultima",
    "artist": "\u7956\u5805 \u6b63\u6176",
    "id": "55JTlu8Uzc3v0hi2iqThiu",
    "added_at": "2023-04-13T02:22:23Z",
    "added_by": "dangreensmith",
    "length_seconds": 430
  },
  {
    "name": "Oblivion",
    "artist": "\u7956\u5805 \u6b63\u6176",
    "id": "11fITg5u1NddciKuiIXEst",
    "added_at": "2023-04-13T02:46:01Z",
    "added_by": "dangreensmith",
    "length_seconds": 479
  },
  {
    "name": "Revenge of the Horde",
    "artist": "\u7956\u5805 \u6b63\u6176",
    "id": "02sRIOljLSa3Xh1trNSRst",
    "added_at": "2023-04-13T02:41:35Z",
    "added_by": "dangreensmith",
    "length_seconds": 214
  },
  {
    "name": "Who Brings Shadow",
    "artist": "\u7956\u5805 \u6b63\u6176",
    "id": "3nYfqm2lnCQQiWKOc0xcP5",
    "added_at": "2023-04-13T02:42:41Z",
    "added_by": "dangreensmith",
    "length_seconds": 565
  },
  {
    "name": "Insatiable",
    "artist": "\u7956\u5805 \u6b63\u6176",
    "id": "1yAQwOO2O3amC5gEWghJwA",
    "added_at": "2023-04-13T02:32:19Z",
    "added_by": "dangreensmith",
    "length_seconds": 305
  },
  {
    "name": "Invincible",
    "artist": "\u7956\u5805 \u6b63\u6176",
    "id": "3OdWhn1bYjWIJBI03dyBP1",
    "added_at": "2023-04-13T02:45:38Z",
    "added_by": "dangreensmith",
    "length_seconds": 361
  },
  {
    "name": "FFVII REMAKE: J-E-N-O-V-A -\u80ce\u52d5- (J-E-N-O-V-A - Quickening)",
    "artist": "Nobuo Uematsu, TADAYOSHI MAKINO",
    "id": "5ZeoTiWvKC5wS08UfgLqsM",
    "added_at": "2023-04-13T02:33:24Z",
    "added_by": "dangreensmith",
    "length_seconds": 379
  },
  {
    "name": "Alien Manifestation",
    "artist": "\u5ca1\u90e8\u5553\u4e00, \u5e06\u8db3\u572d\u543e",
    "id": "1bawDCkXcLpGjRp8LwpD6K",
    "added_at": "2023-04-13T02:53:41Z",
    "added_by": "dangreensmith",
    "length_seconds": 387
  },
  {
    "name": "Song of the Ancients (Atonement)",
    "artist": "\u5ca1\u90e8\u5553\u4e00",
    "id": "0rSc1NL89ymNt2Og5T5vzg",
    "added_at": "2023-04-13T02:22:39Z",
    "added_by": "dangreensmith",
    "length_seconds": 309
  },
  {
    "name": "Emil (Despair)",
    "artist": "\u5e06\u8db3\u572d\u543e, \u77f3\u6ff1 \u7fd4",
    "id": "1kVDDcVsYpQhVzlUDz0Xzq",
    "added_at": "2023-04-13T02:19:16Z",
    "added_by": "dangreensmith",
    "length_seconds": 286
  },
  {
    "name": "The Sound of the End",
    "artist": "\u5e06\u8db3\u572d\u543e",
    "id": "3NZ7NjOVCUTzDbfHKlCant",
    "added_at": "2023-04-13T02:25:37Z",
    "added_by": "dangreensmith",
    "length_seconds": 326
  },
  {
    "name": "Nay! The Honor is All Ours",
    "artist": "Akihiko Narita",
    "id": "2iB2Ixk6tLsr2ULZyhhjPu",
    "added_at": "2023-04-13T02:19:29Z",
    "added_by": "dangreensmith",
    "length_seconds": 296
  },
  {
    "name": "ULTRA VIOLET(\u30cd\u30ed \u30a2\u30f3\u30b8\u30a7\u30ed\u6226)",
    "artist": "Capcom Sound Team",
    "id": "5MgmtxsgI28xyRedapKYBI",
    "added_at": "2023-04-13T02:19:51Z",
    "added_by": "dangreensmith",
    "length_seconds": 201
  },
  {
    "name": "Devil Trigger",
    "artist": "Casey Edwards",
    "id": "29aaQRKHU0wvs90nPBMdlw",
    "added_at": "2023-04-13T02:59:22Z",
    "added_by": "dangreensmith",
    "length_seconds": 405
  },
  {
    "name": "FFVII REMAKE: \u30de\u30c3\u30b9\u30eb\u306a\u8005\u9054 (The Most Muscular)",
    "artist": "Nobuo Uematsu",
    "id": "6rKabiRZpgEOVuj3G3W4iq",
    "added_at": "2023-04-13T02:42:21Z",
    "added_by": "dangreensmith",
    "length_seconds": 100
  },
  {
    "name": "Proof of a Hero - Rise Version",
    "artist": "Capcom Sound Team",
    "id": "7M2zvW8bNWMohjSaNmJibB",
    "added_at": "2023-04-13T02:23:33Z",
    "added_by": "dangreensmith",
    "length_seconds": 212
  },
  {
    "name": "End Times",
    "artist": "Danny Baranowsky",
    "id": "4o1Q4Mogv2Luo34f2L0SJM",
    "added_at": "2023-04-13T02:29:45Z",
    "added_by": "dangreensmith",
    "length_seconds": 114
  },
  {
    "name": "Snow in Summer",
    "artist": "SQUARE ENIX MUSIC",
    "id": "7EFnTKDaM0WiIy6v3NOO97",
    "added_at": "2023-04-13T02:31:57Z",
    "added_by": "dangreensmith",
    "length_seconds": 299
  },
  {
    "name": "Cold Steel Coffin",
    "artist": "SQUARE ENIX MUSIC",
    "id": "0GUo4gPaik5xraYNrhZ9PL",
    "added_at": "2023-04-13T02:43:36Z",
    "added_by": "dangreensmith",
    "length_seconds": 206
  },
  {
    "name": "Song of the Ancients - Lost Androids Mixuxux",
    "artist": "SQUARE ENIX MUSIC",
    "id": "3qnhK5Gr0xdVpT3xhoc8db",
    "added_at": "2023-04-13T02:43:59Z",
    "added_by": "dangreensmith",
    "length_seconds": 335
  },
  {
    "name": "Emil - Ultimate Weapon No.7",
    "artist": "SQUARE ENIX MUSIC",
    "id": "4hhV37jMAKFm7THKHhWW2o",
    "added_at": "2023-04-13T02:44:19Z",
    "added_by": "dangreensmith",
    "length_seconds": 334
  },
  {
    "name": "Shadowlord - Crying Yonah Version",
    "artist": "SQUARE ENIX MUSIC",
    "id": "1XdhS1EB62TRzgvcDlay7L",
    "added_at": "2023-04-13T02:44:23Z",
    "added_by": "dangreensmith",
    "length_seconds": 338
  },
  {
    "name": "Battle B2 (From \"Shin Megami Tensei IV\")",
    "artist": "GillStudio",
    "id": "6cZ7bPZ4m7u1jCmvhX3QLZ",
    "added_at": "2023-04-13T02:49:32Z",
    "added_by": "dangreensmith",
    "length_seconds": 202
  },
  {
    "name": "Battle -dancing crazy murder-",
    "artist": "\u30a2\u30c8\u30e9\u30b9\u30b5\u30a6\u30f3\u30c9\u30c1\u30fc\u30e0, ATLUS GAME MUSIC",
    "id": "2626lsAIrawbGUBovDZZ7Q",
    "added_at": "2023-04-13T02:49:56Z",
    "added_by": "dangreensmith",
    "length_seconds": 270
  },
  {
    "name": "Clash on the Big Bridge (Final Fantasy V)",
    "artist": "Nobuo Uematsu",
    "id": "6ycOc2KczQlbcJGavwkOsl",
    "added_at": "2023-04-13T02:56:12Z",
    "added_by": "dangreensmith",
    "length_seconds": 189
  },
  {
    "name": "The Summit",
    "artist": "Bear McCreary",
    "id": "2FSWaVneLMnzMbyfaBXWvV",
    "added_at": "2023-04-13T10:51:10Z",
    "added_by": "dangreensmith",
    "length_seconds": 198
  }
]